.gitignore
CHANGES.rst
CONTRIBUTORS.rst
README.rst
development.ini
setup.cfg
setup.py
kotti_filestore/__init__.py
kotti_filestore.egg-info/PKG-INFO
kotti_filestore.egg-info/SOURCES.txt
kotti_filestore.egg-info/dependency_links.txt
kotti_filestore.egg-info/entry_points.txt
kotti_filestore.egg-info/not-zip-safe
kotti_filestore.egg-info/requires.txt
kotti_filestore.egg-info/top_level.txt
kotti_filestore/tests/conftest.py
kotti_filestore/tests/test_filesafe.py