Metadata-Version: 1.1
Name: kotti-filestore
Version: 0.1a
Summary: Filesystem storage of BLOBs for Kotti.
Home-page: https://github.com/disko/kotti_filestore
Author: Andreas Kaiser
Author-email: disko@binary-punks.com
License: BSD
Keywords: kotti
Platform: UNKNOWN
Classifier: Environment :: Web Environment
Classifier: Framework :: Pylons
Classifier: Framework :: Pyramid
Classifier: Intended Audience :: Developers
Classifier: License :: OSI Approved :: BSD License
Classifier: Operating System :: OS Independent
Classifier: Programming Language :: Python
Classifier: Programming Language :: Python :: 2.6
Classifier: Programming Language :: Python :: 2.7
Classifier: Topic :: Internet :: WWW/HTTP
Classifier: Topic :: Software Development :: User Interfaces
